{
  "lastUpdated": "2026-03-03T01:19:26.602Z",
  "nextUpdate": "2026-03-03T07:19:26.602Z",
  "campaign": {
    "name": "GDF Uniforme Escolar 2025",
    "siteId": "10491182",
    "siteName": "Uniforme Escolar",
    "startDate": "2026-01-31",
    "endDate": "2026-02-12"
  },
  "summary": {
    "impressions": 2269049,
    "clicks": 923,
    "ctr": 0.04067783463468616,
    "viewableImpressions": 1892007,
    "eligibleImpressions": 2269009,
    "viewabilityRate": 83.38472875162681
  },
  "daily": [
    {
      "date": "2026-01-31",
      "impressions": 143571,
      "clicks": 136,
      "viewable": 119707,
      "eligible": 143571,
      "ctr": 0.09472665092532614,
      "viewabilityRate": 83.37825884057365
    },
    {
      "date": "2026-02-01",
      "impressions": 143304,
      "clicks": 148,
      "viewable": 122183,
      "eligible": 143303,
      "ctr": 0.10327694970133422,
      "viewabilityRate": 85.2619973064067
    },
    {
      "date": "2026-02-02",
      "impressions": 143044,
      "clicks": 63,
      "viewable": 118663,
      "eligible": 143043,
      "ctr": 0.04404239255054389,
      "viewabilityRate": 82.9561740176031
    },
    {
      "date": "2026-02-03",
      "impressions": 133590,
      "clicks": 29,
      "viewable": 113932,
      "eligible": 133590,
      "ctr": 0.021708211692491954,
      "viewabilityRate": 85.28482670858597
    },
    {
      "date": "2026-02-04",
      "impressions": 140571,
      "clicks": 22,
      "viewable": 119362,
      "eligible": 140571,
      "ctr": 0.015650454218864487,
      "viewabilityRate": 84.91225074873195
    },
    {
      "date": "2026-02-05",
      "impressions": 133856,
      "clicks": 24,
      "viewable": 113197,
      "eligible": 133854,
      "ctr": 0.01792971551518049,
      "viewabilityRate": 84.56751385838301
    },
    {
      "date": "2026-02-06",
      "impressions": 146159,
      "clicks": 13,
      "viewable": 121864,
      "eligible": 146159,
      "ctr": 0.008894423196655697,
      "viewabilityRate": 83.37769141825
    },
    {
      "date": "2026-02-07",
      "impressions": 145330,
      "clicks": 21,
      "viewable": 121411,
      "eligible": 145330,
      "ctr": 0.014449872703502375,
      "viewabilityRate": 83.5415949907108
    },
    {
      "date": "2026-02-08",
      "impressions": 146122,
      "clicks": 78,
      "viewable": 128764,
      "eligible": 146122,
      "ctr": 0.05338005228507685,
      "viewabilityRate": 88.12088528763637
    },
    {
      "date": "2026-02-09",
      "impressions": 126966,
      "clicks": 34,
      "viewable": 109054,
      "eligible": 126966,
      "ctr": 0.026778822676937132,
      "viewabilityRate": 85.89228612384417
    },
    {
      "date": "2026-02-10",
      "impressions": 286778,
      "clicks": 120,
      "viewable": 232467,
      "eligible": 286775,
      "ctr": 0.04184421399131035,
      "viewabilityRate": 81.06250544852236
    },
    {
      "date": "2026-02-11",
      "impressions": 288736,
      "clicks": 126,
      "viewable": 234106,
      "eligible": 288711,
      "ctr": 0.043638479441427465,
      "viewabilityRate": 81.08662295513507
    },
    {
      "date": "2026-02-12",
      "impressions": 291022,
      "clicks": 109,
      "viewable": 237297,
      "eligible": 291014,
      "ctr": 0.03745421308354695,
      "viewabilityRate": 81.5414378689685
    }
  ],
  "byFormat": {
    "300x250": {
      "impressions": 973059,
      "clicks": 250,
      "viewable": 761031,
      "eligible": 973052,
      "ctr": 0.025692172828163554,
      "viewabilityRate": 78.21072255131277
    },
    "468x60": {
      "impressions": 71273,
      "clicks": 10,
      "viewable": 61542,
      "eligible": 71273,
      "ctr": 0.014030558556536135,
      "viewabilityRate": 86.34686346863468
    },
    "728x90": {
      "impressions": 1005841,
      "clicks": 183,
      "viewable": 884729,
      "eligible": 1005813,
      "ctr": 0.0181937304206132,
      "viewabilityRate": 87.96157933930064
    },
    "970x250": {
      "impressions": 218876,
      "clicks": 480,
      "viewable": 184705,
      "eligible": 218871,
      "ctr": 0.21930225333065298,
      "viewabilityRate": 84.38989176272781
    }
  },
  "byPersonagem": {
    "menina": {
      "impressions": 797880,
      "clicks": 284,
      "viewable": 662572,
      "eligible": 797864,
      "ctr": 0.03559432496114704,
      "viewabilityRate": 83.04322541184965
    },
    "menino01": {
      "impressions": 789930,
      "clicks": 373,
      "viewable": 664749,
      "eligible": 789917,
      "ctr": 0.047219373868570634,
      "viewabilityRate": 84.15428456407446
    },
    "menino02": {
      "impressions": 681048,
      "clicks": 266,
      "viewable": 564523,
      "eligible": 681037,
      "ctr": 0.039057452631826244,
      "viewabilityRate": 82.89167842569493
    }
  },
  "byReportingLabel": [
    {
      "label": "menino02_H09_C03",
      "personagem": "menino02",
      "headline": "h09",
      "cta": "c03",
      "impressions": 56875,
      "clicks": 41,
      "viewable": 47332,
      "eligible": 56874,
      "ctr": 0.07208791208791208,
      "viewabilityRate": 83.22256215493898
    },
    {
      "label": "menino01_H09_C03",
      "personagem": "menino01",
      "headline": "h09",
      "cta": "c03",
      "impressions": 114422,
      "clicks": 74,
      "viewable": 98363,
      "eligible": 114418,
      "ctr": 0.06467287759346979,
      "viewabilityRate": 85.96811690468283
    },
    {
      "label": "menino02_H07_C02",
      "personagem": "menino02",
      "headline": "h07",
      "cta": "c02",
      "impressions": 54323,
      "clicks": 32,
      "viewable": 45327,
      "eligible": 54323,
      "ctr": 0.05890690867588315,
      "viewabilityRate": 83.43979529849234
    },
    {
      "label": "menino01_H06_C02",
      "personagem": "menino01",
      "headline": "h06",
      "cta": "c02",
      "impressions": 142026,
      "clicks": 82,
      "viewable": 117917,
      "eligible": 142025,
      "ctr": 0.05773590750989255,
      "viewabilityRate": 83.02552367540926
    },
    {
      "label": "menino01_H04_C01",
      "personagem": "menino01",
      "headline": "h04",
      "cta": "c01",
      "impressions": 58148,
      "clicks": 33,
      "viewable": 47951,
      "eligible": 58147,
      "ctr": 0.056751736947100506,
      "viewabilityRate": 82.46513147711833
    },
    {
      "label": "menino01_H05_C01",
      "personagem": "menino01",
      "headline": "h05",
      "cta": "c01",
      "impressions": 66053,
      "clicks": 34,
      "viewable": 56317,
      "eligible": 66053,
      "ctr": 0.05147381648070489,
      "viewabilityRate": 85.26032125717227
    },
    {
      "label": "menino02_H10_C03",
      "personagem": "menino02",
      "headline": "h10",
      "cta": "c03",
      "impressions": 67413,
      "clicks": 34,
      "viewable": 55370,
      "eligible": 67413,
      "ctr": 0.05043537596605995,
      "viewabilityRate": 82.13549315413941
    },
    {
      "label": "menina01_H02_C01",
      "personagem": "menina01",
      "headline": "h02",
      "cta": "c01",
      "impressions": 243892,
      "clicks": 122,
      "viewable": 196104,
      "eligible": 243890,
      "ctr": 0.05002214094763256,
      "viewabilityRate": 80.40674074377793
    },
    {
      "label": "menino01_H08_C03",
      "personagem": "menino01",
      "headline": "h08",
      "cta": "c03",
      "impressions": 74756,
      "clicks": 35,
      "viewable": 61966,
      "eligible": 74754,
      "ctr": 0.046818984429343465,
      "viewabilityRate": 82.89322310511812
    },
    {
      "label": "menino02_H05_C01",
      "personagem": "menino02",
      "headline": "h05",
      "cta": "c01",
      "impressions": 103489,
      "clicks": 48,
      "viewable": 85192,
      "eligible": 103488,
      "ctr": 0.04638174105460484,
      "viewabilityRate": 82.32065553494124
    },
    {
      "label": "menino01_H10_C03",
      "personagem": "menino01",
      "headline": "h10",
      "cta": "c03",
      "impressions": 79818,
      "clicks": 34,
      "viewable": 65803,
      "eligible": 79818,
      "ctr": 0.04259690796562179,
      "viewabilityRate": 82.44130396652383
    },
    {
      "label": "menino01_H01_C01",
      "personagem": "menino01",
      "headline": "h01",
      "cta": "c01",
      "impressions": 111295,
      "clicks": 47,
      "viewable": 96824,
      "eligible": 111292,
      "ctr": 0.04223010916932477,
      "viewabilityRate": 86.99996405851275
    },
    {
      "label": "menina01_H08_C03",
      "personagem": "menina01",
      "headline": "h08",
      "cta": "c03",
      "impressions": 79534,
      "clicks": 29,
      "viewable": 65050,
      "eligible": 79534,
      "ctr": 0.036462393441798475,
      "viewabilityRate": 81.78892046168934
    },
    {
      "label": "menino02_H02_C01",
      "personagem": "menino02",
      "headline": "h02",
      "cta": "c01",
      "impressions": 89186,
      "clicks": 32,
      "viewable": 74159,
      "eligible": 89186,
      "ctr": 0.035880070863139955,
      "viewabilityRate": 83.15094297311238
    },
    {
      "label": "menino02_H08_C03",
      "personagem": "menino02",
      "headline": "h08",
      "cta": "c03",
      "impressions": 77161,
      "clicks": 27,
      "viewable": 62981,
      "eligible": 77159,
      "ctr": 0.03499177045398582,
      "viewabilityRate": 81.62495625915318
    },
    {
      "label": "menina01_H04_C01",
      "personagem": "menina01",
      "headline": "h04",
      "cta": "c01",
      "impressions": 40711,
      "clicks": 14,
      "viewable": 34481,
      "eligible": 40711,
      "ctr": 0.034388740143941436,
      "viewabilityRate": 84.69701063594606
    },
    {
      "label": "menina01_H01_C01",
      "personagem": "menina01",
      "headline": "h01",
      "cta": "c01",
      "impressions": 304743,
      "clicks": 84,
      "viewable": 257421,
      "eligible": 304742,
      "ctr": 0.027564209842391788,
      "viewabilityRate": 84.47178268830683
    },
    {
      "label": "menina01_H03_C01",
      "personagem": "menina01",
      "headline": "h03",
      "cta": "c01",
      "impressions": 129000,
      "clicks": 35,
      "viewable": 109516,
      "eligible": 128987,
      "ctr": 0.02713178294573643,
      "viewabilityRate": 84.90468031662105
    },
    {
      "label": "menino01_H03_C01",
      "personagem": "menino01",
      "headline": "h03",
      "cta": "c01",
      "impressions": 41486,
      "clicks": 11,
      "viewable": 34570,
      "eligible": 41486,
      "ctr": 0.02651496890517283,
      "viewabilityRate": 83.32931591380225
    },
    {
      "label": "menino01_H07_C02",
      "personagem": "menino01",
      "headline": "h07",
      "cta": "c02",
      "impressions": 61659,
      "clicks": 16,
      "viewable": 51304,
      "eligible": 61658,
      "ctr": 0.025949172059228986,
      "viewabilityRate": 83.20736968438808
    },
    {
      "label": "menino02_H04_C01",
      "personagem": "menino02",
      "headline": "h04",
      "cta": "c01",
      "impressions": 43198,
      "clicks": 11,
      "viewable": 35932,
      "eligible": 43197,
      "ctr": 0.025464141858419373,
      "viewabilityRate": 83.18170243303933
    },
    {
      "label": "menino02_H01_C01",
      "personagem": "menino02",
      "headline": "h01",
      "cta": "c01",
      "impressions": 65847,
      "clicks": 16,
      "viewable": 56479,
      "eligible": 65843,
      "ctr": 0.024298753170227953,
      "viewabilityRate": 85.77829078261927
    },
    {
      "label": "menino02_H03_C01",
      "personagem": "menino02",
      "headline": "h03",
      "cta": "c01",
      "impressions": 64197,
      "clicks": 14,
      "viewable": 52269,
      "eligible": 64196,
      "ctr": 0.02180787264202377,
      "viewabilityRate": 81.42096080752695
    },
    {
      "label": "menino02_H06_C02",
      "personagem": "menino02",
      "headline": "h06",
      "cta": "c02",
      "impressions": 59359,
      "clicks": 11,
      "viewable": 49482,
      "eligible": 59358,
      "ctr": 0.018531309489715122,
      "viewabilityRate": 83.36197311230163
    },
    {
      "label": "menino01_H02_C01",
      "personagem": "menino01",
      "headline": "h02",
      "cta": "c01",
      "impressions": 40267,
      "clicks": 7,
      "viewable": 33734,
      "eligible": 40266,
      "ctr": 0.01738396205329426,
      "viewabilityRate": 83.77787711717082
    },
    {
      "label": "(not set)",
      "personagem": "",
      "headline": "",
      "cta": "",
      "impressions": 191,
      "clicks": 0,
      "viewable": 163,
      "eligible": 191,
      "ctr": 0,
      "viewabilityRate": 85.34031413612566
    }
  ],
  "topPerformers": {
    "byCTR": [
      "menino02_H09_C03",
      "menino01_H09_C03",
      "menino02_H07_C02"
    ],
    "byViewability": [
      "menino01_H01_C01",
      "menino01_H09_C03",
      "menino02_H01_C01"
    ],
    "byVolume": [
      "menina01_H01_C01",
      "menina01_H02_C01",
      "menino01_H06_C02"
    ]
  },
  "bySite": [
    {
      "name": "DBM Monks-DV360-DS Media-36727-BR 1481230269-AG - Babel",
      "siteId": "10491182",
      "impressions": 2269049,
      "clicks": 923,
      "viewable": 1892007,
      "eligible": 2269009,
      "ctr": 0.04067783463468616,
      "viewabilityRate": 83.38472875162681
    }
  ],
  "byPlacement": [
    {
      "name": "[P]-[728x90] - Babel- GDF - Cartao Uniforme Escolar 2026",
      "placementId": "439186229",
      "impressions": 1005841,
      "clicks": 183,
      "viewable": 884729,
      "eligible": 1005813,
      "ctr": 0.0181937304206132,
      "viewabilityRate": 87.96157933930064
    },
    {
      "name": "[P]-[300x250] - Babel- GDF - Cartao Uniforme Escolar 2026",
      "placementId": "439015540",
      "impressions": 973059,
      "clicks": 250,
      "viewable": 761031,
      "eligible": 973052,
      "ctr": 0.025692172828163554,
      "viewabilityRate": 78.21072255131277
    },
    {
      "name": "[P]-[970x250] - Babel- GDF - Cartao Uniforme Escolar 2026",
      "placementId": "439186241",
      "impressions": 218876,
      "clicks": 480,
      "viewable": 184705,
      "eligible": 218871,
      "ctr": 0.21930225333065298,
      "viewabilityRate": 84.38989176272781
    },
    {
      "name": "[P]-[468x60] - Babel- GDF - Cartao Uniforme Escolar 2026",
      "placementId": "439186217",
      "impressions": 71273,
      "clicks": 10,
      "viewable": 61542,
      "eligible": 71273,
      "ctr": 0.014030558556536135,
      "viewabilityRate": 86.34686346863468
    }
  ],
  "byCreativePlacement": [
    {
      "creative": "menina01_H01_C01",
      "placement": "[P]-[728x90] - Babel- GDF - Cartao Uniforme Escolar 2026",
      "placementId": "439186229",
      "impressions": 152575,
      "clicks": 19,
      "viewable": 135498,
      "eligible": 152575,
      "ctr": 0.012452892020317876,
      "viewabilityRate": 88.80747173521219
    },
    {
      "creative": "menina01_H02_C01",
      "placement": "[P]-[300x250] - Babel- GDF - Cartao Uniforme Escolar 2026",
      "placementId": "439015540",
      "impressions": 145285,
      "clicks": 37,
      "viewable": 111955,
      "eligible": 145284,
      "ctr": 0.025467185187734453,
      "viewabilityRate": 77.05941466369318
    },
    {
      "creative": "menina01_H01_C01",
      "placement": "[P]-[300x250] - Babel- GDF - Cartao Uniforme Escolar 2026",
      "placementId": "439015540",
      "impressions": 128134,
      "clicks": 36,
      "viewable": 101206,
      "eligible": 128134,
      "ctr": 0.02809558743190722,
      "viewabilityRate": 78.98450060093339
    },
    {
      "creative": "menina01_H03_C01",
      "placement": "[P]-[728x90] - Babel- GDF - Cartao Uniforme Escolar 2026",
      "placementId": "439186229",
      "impressions": 89862,
      "clicks": 15,
      "viewable": 77886,
      "eligible": 89849,
      "ctr": 0.016692261467583628,
      "viewabilityRate": 86.68543890304845
    },
    {
      "creative": "menino01_H01_C01",
      "placement": "[P]-[728x90] - Babel- GDF - Cartao Uniforme Escolar 2026",
      "placementId": "439186229",
      "impressions": 86461,
      "clicks": 20,
      "viewable": 76313,
      "eligible": 86458,
      "ctr": 0.023131816657221176,
      "viewabilityRate": 88.26597885678595
    },
    {
      "creative": "menino01_H09_C03",
      "placement": "[P]-[728x90] - Babel- GDF - Cartao Uniforme Escolar 2026",
      "placementId": "439186229",
      "impressions": 83603,
      "clicks": 30,
      "viewable": 73352,
      "eligible": 83600,
      "ctr": 0.0358838797650802,
      "viewabilityRate": 87.74162679425838
    },
    {
      "creative": "menino01_H06_C02",
      "placement": "[P]-[300x250] - Babel- GDF - Cartao Uniforme Escolar 2026",
      "placementId": "439015540",
      "impressions": 66844,
      "clicks": 18,
      "viewable": 52081,
      "eligible": 66844,
      "ctr": 0.026928370534378555,
      "viewabilityRate": 77.91424810005387
    },
    {
      "creative": "menino01_H06_C02",
      "placement": "[P]-[728x90] - Babel- GDF - Cartao Uniforme Escolar 2026",
      "placementId": "439186229",
      "impressions": 57296,
      "clicks": 12,
      "viewable": 50812,
      "eligible": 57295,
      "ctr": 0.020943870427254957,
      "viewabilityRate": 88.68487651627541
    },
    {
      "creative": "menino02_H08_C03",
      "placement": "[P]-[300x250] - Babel- GDF - Cartao Uniforme Escolar 2026",
      "placementId": "439015540",
      "impressions": 56117,
      "clicks": 18,
      "viewable": 44447,
      "eligible": 56117,
      "ctr": 0.032075841545342765,
      "viewabilityRate": 79.20416273143611
    },
    {
      "creative": "menina01_H02_C01",
      "placement": "[P]-[728x90] - Babel- GDF - Cartao Uniforme Escolar 2026",
      "placementId": "439186229",
      "impressions": 55842,
      "clicks": 13,
      "viewable": 48385,
      "eligible": 55842,
      "ctr": 0.02327996848250421,
      "viewabilityRate": 86.64625192507431
    },
    {
      "creative": "menino02_H05_C01",
      "placement": "[P]-[300x250] - Babel- GDF - Cartao Uniforme Escolar 2026",
      "placementId": "439015540",
      "impressions": 55833,
      "clicks": 17,
      "viewable": 44048,
      "eligible": 55833,
      "ctr": 0.03044794297279387,
      "viewabilityRate": 78.89241129797789
    },
    {
      "creative": "menino02_H02_C01",
      "placement": "[P]-[300x250] - Babel- GDF - Cartao Uniforme Escolar 2026",
      "placementId": "439015540",
      "impressions": 49263,
      "clicks": 19,
      "viewable": 38897,
      "eligible": 49263,
      "ctr": 0.03856849968536224,
      "viewabilityRate": 78.9578385400808
    },
    {
      "creative": "menina01_H08_C03",
      "placement": "[P]-[300x250] - Babel- GDF - Cartao Uniforme Escolar 2026",
      "placementId": "439015540",
      "impressions": 48353,
      "clicks": 13,
      "viewable": 37912,
      "eligible": 48353,
      "ctr": 0.026885612061299198,
      "viewabilityRate": 78.40671726676732
    },
    {
      "creative": "menino02_H01_C01",
      "placement": "[P]-[728x90] - Babel- GDF - Cartao Uniforme Escolar 2026",
      "placementId": "439186229",
      "impressions": 48280,
      "clicks": 9,
      "viewable": 42404,
      "eligible": 48278,
      "ctr": 0.018641259320629662,
      "viewabilityRate": 87.83296739715813
    },
    {
      "creative": "menino01_H10_C03",
      "placement": "[P]-[300x250] - Babel- GDF - Cartao Uniforme Escolar 2026",
      "placementId": "439015540",
      "impressions": 42174,
      "clicks": 7,
      "viewable": 32750,
      "eligible": 42174,
      "ctr": 0.016597903921847585,
      "viewabilityRate": 77.65447906292977
    },
    {
      "creative": "menino02_H03_C01",
      "placement": "[P]-[300x250] - Babel- GDF - Cartao Uniforme Escolar 2026",
      "placementId": "439015540",
      "impressions": 38670,
      "clicks": 11,
      "viewable": 29784,
      "eligible": 38669,
      "ctr": 0.028445823635893455,
      "viewabilityRate": 77.0229382709664
    },
    {
      "creative": "menina01_H02_C01",
      "placement": "[P]-[970x250] - Babel- GDF - Cartao Uniforme Escolar 2026",
      "placementId": "439186241",
      "impressions": 37693,
      "clicks": 71,
      "viewable": 31660,
      "eligible": 37692,
      "ctr": 0.18836388719390867,
      "viewabilityRate": 83.99660405391064
    },
    {
      "creative": "menino02_H05_C01",
      "placement": "[P]-[728x90] - Babel- GDF - Cartao Uniforme Escolar 2026",
      "placementId": "439186229",
      "impressions": 37024,
      "clicks": 12,
      "viewable": 32099,
      "eligible": 37023,
      "ctr": 0.032411408815903195,
      "viewabilityRate": 86.70015936039759
    },
    {
      "creative": "menino01_H05_C01",
      "placement": "[P]-[728x90] - Babel- GDF - Cartao Uniforme Escolar 2026",
      "placementId": "439186229",
      "impressions": 36109,
      "clicks": 7,
      "viewable": 32223,
      "eligible": 36109,
      "ctr": 0.019385748705308927,
      "viewabilityRate": 89.23814007588136
    },
    {
      "creative": "menino01_H08_C03",
      "placement": "[P]-[300x250] - Babel- GDF - Cartao Uniforme Escolar 2026",
      "placementId": "439015540",
      "impressions": 35947,
      "clicks": 12,
      "viewable": 28237,
      "eligible": 35946,
      "ctr": 0.03338247976187164,
      "viewabilityRate": 78.55394202414733
    },
    {
      "creative": "menino02_H10_C03",
      "placement": "[P]-[300x250] - Babel- GDF - Cartao Uniforme Escolar 2026",
      "placementId": "439015540",
      "impressions": 31583,
      "clicks": 5,
      "viewable": 24399,
      "eligible": 31583,
      "ctr": 0.015831301649621633,
      "viewabilityRate": 77.25358578982365
    },
    {
      "creative": "menino02_H02_C01",
      "placement": "[P]-[728x90] - Babel- GDF - Cartao Uniforme Escolar 2026",
      "placementId": "439186229",
      "impressions": 31550,
      "clicks": 2,
      "viewable": 28064,
      "eligible": 31550,
      "ctr": 0.006339144215530904,
      "viewabilityRate": 88.95087163232964
    },
    {
      "creative": "menino01_H07_C02",
      "placement": "[P]-[728x90] - Babel- GDF - Cartao Uniforme Escolar 2026",
      "placementId": "439186229",
      "impressions": 30445,
      "clicks": 7,
      "viewable": 26594,
      "eligible": 30444,
      "ctr": 0.022992281162752502,
      "viewabilityRate": 87.35382998291946
    },
    {
      "creative": "menino01_H04_C01",
      "placement": "[P]-[300x250] - Babel- GDF - Cartao Uniforme Escolar 2026",
      "placementId": "439015540",
      "impressions": 29482,
      "clicks": 7,
      "viewable": 23190,
      "eligible": 29481,
      "ctr": 0.02374330099721864,
      "viewabilityRate": 78.66083240052916
    },
    {
      "creative": "menino01_H08_C03",
      "placement": "[P]-[728x90] - Babel- GDF - Cartao Uniforme Escolar 2026",
      "placementId": "439186229",
      "impressions": 29463,
      "clicks": 2,
      "viewable": 25753,
      "eligible": 29463,
      "ctr": 0.006788174999151479,
      "viewabilityRate": 87.407935376574
    },
    {
      "creative": "menino02_H06_C02",
      "placement": "[P]-[728x90] - Babel- GDF - Cartao Uniforme Escolar 2026",
      "placementId": "439186229",
      "impressions": 28791,
      "clicks": 3,
      "viewable": 25241,
      "eligible": 28791,
      "ctr": 0.010419922892570594,
      "viewabilityRate": 87.66975791045813
    },
    {
      "creative": "menino01_H10_C03",
      "placement": "[P]-[728x90] - Babel- GDF - Cartao Uniforme Escolar 2026",
      "placementId": "439186229",
      "impressions": 27169,
      "clicks": 4,
      "viewable": 24309,
      "eligible": 27169,
      "ctr": 0.014722661857263794,
      "viewabilityRate": 89.47329677205639
    },
    {
      "creative": "menino02_H09_C03",
      "placement": "[P]-[300x250] - Babel- GDF - Cartao Uniforme Escolar 2026",
      "placementId": "439015540",
      "impressions": 26135,
      "clicks": 8,
      "viewable": 20718,
      "eligible": 26135,
      "ctr": 0.03061029271092405,
      "viewabilityRate": 79.27300554811555
    },
    {
      "creative": "menino02_H06_C02",
      "placement": "[P]-[300x250] - Babel- GDF - Cartao Uniforme Escolar 2026",
      "placementId": "439015540",
      "impressions": 25919,
      "clicks": 7,
      "viewable": 20302,
      "eligible": 25918,
      "ctr": 0.02700721478452101,
      "viewabilityRate": 78.33166139362605
    },
    {
      "creative": "menina01_H03_C01",
      "placement": "[P]-[300x250] - Babel- GDF - Cartao Uniforme Escolar 2026",
      "placementId": "439015540",
      "impressions": 25082,
      "clicks": 8,
      "viewable": 19486,
      "eligible": 25082,
      "ctr": 0.03189538314329001,
      "viewabilityRate": 77.68917949126863
    },
    {
      "creative": "menino01_H07_C02",
      "placement": "[P]-[300x250] - Babel- GDF - Cartao Uniforme Escolar 2026",
      "placementId": "439015540",
      "impressions": 24185,
      "clicks": 4,
      "viewable": 18853,
      "eligible": 24185,
      "ctr": 0.016539177175935497,
      "viewabilityRate": 77.95327682447798
    },
    {
      "creative": "menino02_H07_C02",
      "placement": "[P]-[728x90] - Babel- GDF - Cartao Uniforme Escolar 2026",
      "placementId": "439186229",
      "impressions": 23860,
      "clicks": 5,
      "viewable": 20965,
      "eligible": 23860,
      "ctr": 0.020955574182732608,
      "viewabilityRate": 87.86672254819781
    },
    {
      "creative": "menino02_H10_C03",
      "placement": "[P]-[728x90] - Babel- GDF - Cartao Uniforme Escolar 2026",
      "placementId": "439186229",
      "impressions": 23826,
      "clicks": 3,
      "viewable": 20936,
      "eligible": 23826,
      "ctr": 0.012591286829513975,
      "viewabilityRate": 87.87039368756821
    },
    {
      "creative": "menina01_H04_C01",
      "placement": "[P]-[728x90] - Babel- GDF - Cartao Uniforme Escolar 2026",
      "placementId": "439186229",
      "impressions": 22814,
      "clicks": 3,
      "viewable": 20001,
      "eligible": 22814,
      "ctr": 0.013149820285789426,
      "viewabilityRate": 87.66985184535811
    },
    {
      "creative": "menino02_H04_C01",
      "placement": "[P]-[300x250] - Babel- GDF - Cartao Uniforme Escolar 2026",
      "placementId": "439015540",
      "impressions": 22326,
      "clicks": 6,
      "viewable": 17762,
      "eligible": 22326,
      "ctr": 0.026874496103198062,
      "viewabilityRate": 79.557466630834
    },
    {
      "creative": "menino02_H03_C01",
      "placement": "[P]-[728x90] - Babel- GDF - Cartao Uniforme Escolar 2026",
      "placementId": "439186229",
      "impressions": 22306,
      "clicks": 2,
      "viewable": 19692,
      "eligible": 22306,
      "ctr": 0.008966197435667534,
      "viewabilityRate": 88.28117995158253
    },
    {
      "creative": "menina01_H08_C03",
      "placement": "[P]-[728x90] - Babel- GDF - Cartao Uniforme Escolar 2026",
      "placementId": "439186229",
      "impressions": 22088,
      "clicks": 5,
      "viewable": 19511,
      "eligible": 22088,
      "ctr": 0.022636725823976817,
      "viewabilityRate": 88.33303151032234
    },
    {
      "creative": "menino01_H03_C01",
      "placement": "[P]-[728x90] - Babel- GDF - Cartao Uniforme Escolar 2026",
      "placementId": "439186229",
      "impressions": 20304,
      "clicks": 2,
      "viewable": 17707,
      "eligible": 20304,
      "ctr": 0.009850275807722617,
      "viewabilityRate": 87.20941686367219
    },
    {
      "creative": "menino02_H07_C02",
      "placement": "[P]-[300x250] - Babel- GDF - Cartao Uniforme Escolar 2026",
      "placementId": "439015540",
      "impressions": 19540,
      "clicks": 5,
      "viewable": 15325,
      "eligible": 19540,
      "ctr": 0.0255885363357216,
      "viewabilityRate": 78.4288638689867
    },
    {
      "creative": "menino01_H05_C01",
      "placement": "[P]-[300x250] - Babel- GDF - Cartao Uniforme Escolar 2026",
      "placementId": "439015540",
      "impressions": 17735,
      "clicks": 2,
      "viewable": 13750,
      "eligible": 17735,
      "ctr": 0.011277135607555682,
      "viewabilityRate": 77.5303073019453
    },
    {
      "creative": "menino01_H02_C01",
      "placement": "[P]-[300x250] - Babel- GDF - Cartao Uniforme Escolar 2026",
      "placementId": "439015540",
      "impressions": 17328,
      "clicks": 3,
      "viewable": 13666,
      "eligible": 17328,
      "ctr": 0.01731301939058172,
      "viewabilityRate": 78.86657433056325
    },
    {
      "creative": "menino01_H03_C01",
      "placement": "[P]-[300x250] - Babel- GDF - Cartao Uniforme Escolar 2026",
      "placementId": "439015540",
      "impressions": 16343,
      "clicks": 4,
      "viewable": 12750,
      "eligible": 16343,
      "ctr": 0.024475310530502354,
      "viewabilityRate": 78.01505231597626
    },
    {
      "creative": "menino01_H02_C01",
      "placement": "[P]-[728x90] - Babel- GDF - Cartao Uniforme Escolar 2026",
      "placementId": "439186229",
      "impressions": 16134,
      "clicks": 3,
      "viewable": 14193,
      "eligible": 16134,
      "ctr": 0.01859427296392711,
      "viewabilityRate": 87.96950539233916
    },
    {
      "creative": "menino02_H04_C01",
      "placement": "[P]-[728x90] - Babel- GDF - Cartao Uniforme Escolar 2026",
      "placementId": "439186229",
      "impressions": 16038,
      "clicks": 1,
      "viewable": 14010,
      "eligible": 16037,
      "ctr": 0.006235191420376606,
      "viewabilityRate": 87.36047889256096
    },
    {
      "creative": "menino01_H04_C01",
      "placement": "[P]-[728x90] - Babel- GDF - Cartao Uniforme Escolar 2026",
      "placementId": "439186229",
      "impressions": 15765,
      "clicks": 2,
      "viewable": 13702,
      "eligible": 15765,
      "ctr": 0.012686330478908976,
      "viewabilityRate": 86.9140501110054
    },
    {
      "creative": "menino01_H06_C02",
      "placement": "[P]-[970x250] - Babel- GDF - Cartao Uniforme Escolar 2026",
      "placementId": "439186241",
      "impressions": 15599,
      "clicks": 52,
      "viewable": 13023,
      "eligible": 15599,
      "ctr": 0.3333547022245016,
      "viewabilityRate": 83.48612090518624
    },
    {
      "creative": "menina01_H01_C01",
      "placement": "[P]-[970x250] - Babel- GDF - Cartao Uniforme Escolar 2026",
      "placementId": "439186241",
      "impressions": 15515,
      "clicks": 29,
      "viewable": 13154,
      "eligible": 15514,
      "ctr": 0.1869158878504673,
      "viewabilityRate": 84.78793347943792
    },
    {
      "creative": "menino02_H09_C03",
      "placement": "[P]-[728x90] - Babel- GDF - Cartao Uniforme Escolar 2026",
      "placementId": "439186229",
      "impressions": 14829,
      "clicks": 2,
      "viewable": 13114,
      "eligible": 14828,
      "ctr": 0.013487086115044844,
      "viewabilityRate": 88.44078769894793
    },
    {
      "creative": "menino01_H09_C03",
      "placement": "[P]-[970x250] - Babel- GDF - Cartao Uniforme Escolar 2026",
      "placementId": "439186241",
      "impressions": 14818,
      "clicks": 44,
      "viewable": 12580,
      "eligible": 14818,
      "ctr": 0.2969361587258739,
      "viewabilityRate": 84.89674719935213
    },
    {
      "creative": "menino01_H09_C03",
      "placement": "[P]-[300x250] - Babel- GDF - Cartao Uniforme Escolar 2026",
      "placementId": "439015540",
      "impressions": 14155,
      "clicks": 0,
      "viewable": 10865,
      "eligible": 14154,
      "ctr": 0,
      "viewabilityRate": 76.76275257877631
    },
    {
      "creative": "menino02_H09_C03",
      "placement": "[P]-[970x250] - Babel- GDF - Cartao Uniforme Escolar 2026",
      "placementId": "439186241",
      "impressions": 14078,
      "clicks": 31,
      "viewable": 11928,
      "eligible": 14078,
      "ctr": 0.22020173320073874,
      "viewabilityRate": 84.72794431027134
    },
    {
      "creative": "menino02_H08_C03",
      "placement": "[P]-[728x90] - Babel- GDF - Cartao Uniforme Escolar 2026",
      "placementId": "439186229",
      "impressions": 13316,
      "clicks": 0,
      "viewable": 11882,
      "eligible": 13314,
      "ctr": 0,
      "viewabilityRate": 89.24440438636022
    },
    {
      "creative": "menino02_H01_C01",
      "placement": "[P]-[300x250] - Babel- GDF - Cartao Uniforme Escolar 2026",
      "placementId": "439015540",
      "impressions": 12571,
      "clicks": 0,
      "viewable": 9827,
      "eligible": 12570,
      "ctr": 0,
      "viewabilityRate": 78.17820206841687
    },
    {
      "creative": "menino01_H01_C01",
      "placement": "[P]-[300x250] - Babel- GDF - Cartao Uniforme Escolar 2026",
      "placementId": "439015540",
      "impressions": 12401,
      "clicks": 2,
      "viewable": 9699,
      "eligible": 12401,
      "ctr": 0.016127731634545603,
      "viewabilityRate": 78.2114345617289
    },
    {
      "creative": "menina01_H04_C01",
      "placement": "[P]-[300x250] - Babel- GDF - Cartao Uniforme Escolar 2026",
      "placementId": "439015540",
      "impressions": 11577,
      "clicks": 1,
      "viewable": 9063,
      "eligible": 11577,
      "ctr": 0.008637816360024185,
      "viewabilityRate": 78.28452967089919
    },
    {
      "creative": "menino01_H04_C01",
      "placement": "[P]-[970x250] - Babel- GDF - Cartao Uniforme Escolar 2026",
      "placementId": "439186241",
      "impressions": 11095,
      "clicks": 24,
      "viewable": 9494,
      "eligible": 11095,
      "ctr": 0.2163136547994592,
      "viewabilityRate": 85.57007661108608
    },
    {
      "creative": "menino01_H05_C01",
      "placement": "[P]-[970x250] - Babel- GDF - Cartao Uniforme Escolar 2026",
      "placementId": "439186241",
      "impressions": 10407,
      "clicks": 25,
      "viewable": 8762,
      "eligible": 10407,
      "ctr": 0.24022292687614108,
      "viewabilityRate": 84.19333141154992
    },
    {
      "creative": "menino01_H01_C01",
      "placement": "[P]-[970x250] - Babel- GDF - Cartao Uniforme Escolar 2026",
      "placementId": "439186241",
      "impressions": 10122,
      "clicks": 24,
      "viewable": 8799,
      "eligible": 10122,
      "ctr": 0.23710729104919975,
      "viewabilityRate": 86.92946058091286
    },
    {
      "creative": "menino02_H10_C03",
      "placement": "[P]-[970x250] - Babel- GDF - Cartao Uniforme Escolar 2026",
      "placementId": "439186241",
      "impressions": 10117,
      "clicks": 26,
      "viewable": 8416,
      "eligible": 10117,
      "ctr": 0.2569931797963823,
      "viewabilityRate": 83.18671542947514
    },
    {
      "creative": "menino02_H07_C02",
      "placement": "[P]-[970x250] - Babel- GDF - Cartao Uniforme Escolar 2026",
      "placementId": "439186241",
      "impressions": 9034,
      "clicks": 21,
      "viewable": 7399,
      "eligible": 9034,
      "ctr": 0.23245516936019484,
      "viewabilityRate": 81.90170467124197
    },
    {
      "creative": "menino02_H05_C01",
      "placement": "[P]-[970x250] - Babel- GDF - Cartao Uniforme Escolar 2026",
      "placementId": "439186241",
      "impressions": 8883,
      "clicks": 19,
      "viewable": 7541,
      "eligible": 8883,
      "ctr": 0.21389170325340537,
      "viewabilityRate": 84.89249127547
    },
    {
      "creative": "menino01_H10_C03",
      "placement": "[P]-[970x250] - Babel- GDF - Cartao Uniforme Escolar 2026",
      "placementId": "439186241",
      "impressions": 8700,
      "clicks": 22,
      "viewable": 7226,
      "eligible": 8700,
      "ctr": 0.2528735632183908,
      "viewabilityRate": 83.05747126436782
    },
    {
      "creative": "menina01_H01_C01",
      "placement": "[P]-[468x60] - Babel- GDF - Cartao Uniforme Escolar 2026",
      "placementId": "439186217",
      "impressions": 8519,
      "clicks": 0,
      "viewable": 7563,
      "eligible": 8519,
      "ctr": 0,
      "viewabilityRate": 88.77802558985796
    },
    {
      "creative": "menina01_H03_C01",
      "placement": "[P]-[468x60] - Babel- GDF - Cartao Uniforme Escolar 2026",
      "placementId": "439186217",
      "impressions": 8418,
      "clicks": 1,
      "viewable": 7253,
      "eligible": 8418,
      "ctr": 0.011879306248515086,
      "viewabilityRate": 86.16060822047993
    },
    {
      "creative": "menino01_H08_C03",
      "placement": "[P]-[970x250] - Babel- GDF - Cartao Uniforme Escolar 2026",
      "placementId": "439186241",
      "impressions": 7592,
      "clicks": 21,
      "viewable": 6461,
      "eligible": 7591,
      "ctr": 0.2766069546891465,
      "viewabilityRate": 85.11395073112897
    },
    {
      "creative": "menino02_H02_C01",
      "placement": "[P]-[970x250] - Babel- GDF - Cartao Uniforme Escolar 2026",
      "placementId": "439186241",
      "impressions": 6021,
      "clicks": 11,
      "viewable": 5147,
      "eligible": 6021,
      "ctr": 0.18269390466699884,
      "viewabilityRate": 85.48413884736755
    },
    {
      "creative": "menina01_H08_C03",
      "placement": "[P]-[970x250] - Babel- GDF - Cartao Uniforme Escolar 2026",
      "placementId": "439186241",
      "impressions": 5712,
      "clicks": 10,
      "viewable": 4690,
      "eligible": 5712,
      "ctr": 0.1750700280112045,
      "viewabilityRate": 82.1078431372549
    },
    {
      "creative": "menina01_H03_C01",
      "placement": "[P]-[970x250] - Babel- GDF - Cartao Uniforme Escolar 2026",
      "placementId": "439186241",
      "impressions": 5638,
      "clicks": 11,
      "viewable": 4891,
      "eligible": 5638,
      "ctr": 0.1951046470379567,
      "viewabilityRate": 86.7506207875133
    },
    {
      "creative": "menino01_H07_C02",
      "placement": "[P]-[970x250] - Babel- GDF - Cartao Uniforme Escolar 2026",
      "placementId": "439186241",
      "impressions": 5212,
      "clicks": 5,
      "viewable": 4300,
      "eligible": 5212,
      "ctr": 0.09593246354566384,
      "viewabilityRate": 82.5019186492709
    },
    {
      "creative": "menina01_H02_C01",
      "placement": "[P]-[468x60] - Babel- GDF - Cartao Uniforme Escolar 2026",
      "placementId": "439186217",
      "impressions": 5072,
      "clicks": 1,
      "viewable": 4104,
      "eligible": 5072,
      "ctr": 0.01971608832807571,
      "viewabilityRate": 80.91482649842271
    },
    {
      "creative": "menina01_H04_C01",
      "placement": "[P]-[970x250] - Babel- GDF - Cartao Uniforme Escolar 2026",
      "placementId": "439186241",
      "impressions": 4815,
      "clicks": 10,
      "viewable": 4131,
      "eligible": 4815,
      "ctr": 0.20768431983385255,
      "viewabilityRate": 85.79439252336448
    },
    {
      "creative": "menino02_H08_C03",
      "placement": "[P]-[468x60] - Babel- GDF - Cartao Uniforme Escolar 2026",
      "placementId": "439186217",
      "impressions": 4753,
      "clicks": 2,
      "viewable": 4135,
      "eligible": 4753,
      "ctr": 0.042078687144961074,
      "viewabilityRate": 86.99768567220703
    },
    {
      "creative": "menino01_H02_C01",
      "placement": "[P]-[468x60] - Babel- GDF - Cartao Uniforme Escolar 2026",
      "placementId": "439186217",
      "impressions": 4752,
      "clicks": 0,
      "viewable": 4147,
      "eligible": 4752,
      "ctr": 0,
      "viewabilityRate": 87.26851851851852
    },
    {
      "creative": "menina01_H08_C03",
      "placement": "[P]-[468x60] - Babel- GDF - Cartao Uniforme Escolar 2026",
      "placementId": "439186217",
      "impressions": 3381,
      "clicks": 1,
      "viewable": 2937,
      "eligible": 3381,
      "ctr": 0.02957704821058858,
      "viewabilityRate": 86.86779059449867
    },
    {
      "creative": "menino01_H03_C01",
      "placement": "[P]-[970x250] - Babel- GDF - Cartao Uniforme Escolar 2026",
      "placementId": "439186241",
      "impressions": 3031,
      "clicks": 5,
      "viewable": 2548,
      "eligible": 3031,
      "ctr": 0.16496205872649292,
      "viewabilityRate": 84.06466512702079
    },
    {
      "creative": "menino02_H08_C03",
      "placement": "[P]-[970x250] - Babel- GDF - Cartao Uniforme Escolar 2026",
      "placementId": "439186241",
      "impressions": 2975,
      "clicks": 7,
      "viewable": 2517,
      "eligible": 2975,
      "ctr": 0.2352941176470588,
      "viewabilityRate": 84.60504201680672
    },
    {
      "creative": "menino02_H04_C01",
      "placement": "[P]-[970x250] - Babel- GDF - Cartao Uniforme Escolar 2026",
      "placementId": "439186241",
      "impressions": 2866,
      "clicks": 2,
      "viewable": 2466,
      "eligible": 2866,
      "ctr": 0.06978367062107467,
      "viewabilityRate": 86.04326587578507
    },
    {
      "creative": "menino02_H06_C02",
      "placement": "[P]-[970x250] - Babel- GDF - Cartao Uniforme Escolar 2026",
      "placementId": "439186241",
      "impressions": 2792,
      "clicks": 1,
      "viewable": 2366,
      "eligible": 2792,
      "ctr": 0.03581661891117478,
      "viewabilityRate": 84.74212034383955
    },
    {
      "creative": "menino02_H01_C01",
      "placement": "[P]-[970x250] - Babel- GDF - Cartao Uniforme Escolar 2026",
      "placementId": "439186241",
      "impressions": 2697,
      "clicks": 7,
      "viewable": 2252,
      "eligible": 2696,
      "ctr": 0.25954764553207266,
      "viewabilityRate": 83.53115727002968
    },
    {
      "creative": "menino02_H02_C01",
      "placement": "[P]-[468x60] - Babel- GDF - Cartao Uniforme Escolar 2026",
      "placementId": "439186217",
      "impressions": 2352,
      "clicks": 0,
      "viewable": 2051,
      "eligible": 2352,
      "ctr": 0,
      "viewabilityRate": 87.20238095238095
    },
    {
      "creative": "menino01_H01_C01",
      "placement": "[P]-[468x60] - Babel- GDF - Cartao Uniforme Escolar 2026",
      "placementId": "439186217",
      "impressions": 2311,
      "clicks": 1,
      "viewable": 2013,
      "eligible": 2311,
      "ctr": 0.043271311120726956,
      "viewabilityRate": 87.10514928602336
    },
    {
      "creative": "menino02_H01_C01",
      "placement": "[P]-[468x60] - Babel- GDF - Cartao Uniforme Escolar 2026",
      "placementId": "439186217",
      "impressions": 2299,
      "clicks": 0,
      "viewable": 1996,
      "eligible": 2299,
      "ctr": 0,
      "viewabilityRate": 86.820356676816
    },
    {
      "creative": "menino01_H06_C02",
      "placement": "[P]-[468x60] - Babel- GDF - Cartao Uniforme Escolar 2026",
      "placementId": "439186217",
      "impressions": 2287,
      "clicks": 0,
      "viewable": 2001,
      "eligible": 2287,
      "ctr": 0,
      "viewabilityRate": 87.4945343244425
    },
    {
      "creative": "menino01_H02_C01",
      "placement": "[P]-[970x250] - Babel- GDF - Cartao Uniforme Escolar 2026",
      "placementId": "439186241",
      "impressions": 2053,
      "clicks": 1,
      "viewable": 1728,
      "eligible": 2052,
      "ctr": 0.04870920603994155,
      "viewabilityRate": 84.21052631578947
    },
    {
      "creative": "menino02_H04_C01",
      "placement": "[P]-[468x60] - Babel- GDF - Cartao Uniforme Escolar 2026",
      "placementId": "439186217",
      "impressions": 1968,
      "clicks": 2,
      "viewable": 1694,
      "eligible": 1968,
      "ctr": 0.10162601626016261,
      "viewabilityRate": 86.07723577235772
    },
    {
      "creative": "menino02_H07_C02",
      "placement": "[P]-[468x60] - Babel- GDF - Cartao Uniforme Escolar 2026",
      "placementId": "439186217",
      "impressions": 1889,
      "clicks": 1,
      "viewable": 1638,
      "eligible": 1889,
      "ctr": 0.05293806246691372,
      "viewabilityRate": 86.71254632080466
    },
    {
      "creative": "menino02_H10_C03",
      "placement": "[P]-[468x60] - Babel- GDF - Cartao Uniforme Escolar 2026",
      "placementId": "439186217",
      "impressions": 1887,
      "clicks": 0,
      "viewable": 1619,
      "eligible": 1887,
      "ctr": 0,
      "viewabilityRate": 85.7975622681505
    },
    {
      "creative": "menino02_H06_C02",
      "placement": "[P]-[468x60] - Babel- GDF - Cartao Uniforme Escolar 2026",
      "placementId": "439186217",
      "impressions": 1857,
      "clicks": 0,
      "viewable": 1573,
      "eligible": 1857,
      "ctr": 0,
      "viewabilityRate": 84.70651588583738
    },
    {
      "creative": "menino01_H09_C03",
      "placement": "[P]-[468x60] - Babel- GDF - Cartao Uniforme Escolar 2026",
      "placementId": "439186217",
      "impressions": 1846,
      "clicks": 0,
      "viewable": 1566,
      "eligible": 1846,
      "ctr": 0,
      "viewabilityRate": 84.8320693391116
    },
    {
      "creative": "menino02_H09_C03",
      "placement": "[P]-[468x60] - Babel- GDF - Cartao Uniforme Escolar 2026",
      "placementId": "439186217",
      "impressions": 1833,
      "clicks": 0,
      "viewable": 1572,
      "eligible": 1833,
      "ctr": 0,
      "viewabilityRate": 85.76104746317512
    },
    {
      "creative": "menino02_H03_C01",
      "placement": "[P]-[468x60] - Babel- GDF - Cartao Uniforme Escolar 2026",
      "placementId": "439186217",
      "impressions": 1830,
      "clicks": 0,
      "viewable": 1586,
      "eligible": 1830,
      "ctr": 0,
      "viewabilityRate": 86.66666666666667
    },
    {
      "creative": "menino01_H07_C02",
      "placement": "[P]-[468x60] - Babel- GDF - Cartao Uniforme Escolar 2026",
      "placementId": "439186217",
      "impressions": 1817,
      "clicks": 0,
      "viewable": 1557,
      "eligible": 1817,
      "ctr": 0,
      "viewabilityRate": 85.69069895432031
    },
    {
      "creative": "menino01_H03_C01",
      "placement": "[P]-[468x60] - Babel- GDF - Cartao Uniforme Escolar 2026",
      "placementId": "439186217",
      "impressions": 1808,
      "clicks": 0,
      "viewable": 1565,
      "eligible": 1808,
      "ctr": 0,
      "viewabilityRate": 86.55973451327434
    },
    {
      "creative": "menino01_H04_C01",
      "placement": "[P]-[468x60] - Babel- GDF - Cartao Uniforme Escolar 2026",
      "placementId": "439186217",
      "impressions": 1806,
      "clicks": 0,
      "viewable": 1565,
      "eligible": 1806,
      "ctr": 0,
      "viewabilityRate": 86.65559246954597
    },
    {
      "creative": "menino01_H05_C01",
      "placement": "[P]-[468x60] - Babel- GDF - Cartao Uniforme Escolar 2026",
      "placementId": "439186217",
      "impressions": 1802,
      "clicks": 0,
      "viewable": 1582,
      "eligible": 1802,
      "ctr": 0,
      "viewabilityRate": 87.79134295227526
    },
    {
      "creative": "menino01_H10_C03",
      "placement": "[P]-[468x60] - Babel- GDF - Cartao Uniforme Escolar 2026",
      "placementId": "439186217",
      "impressions": 1775,
      "clicks": 1,
      "viewable": 1518,
      "eligible": 1775,
      "ctr": 0.056338028169014086,
      "viewabilityRate": 85.52112676056338
    },
    {
      "creative": "menino01_H08_C03",
      "placement": "[P]-[468x60] - Babel- GDF - Cartao Uniforme Escolar 2026",
      "placementId": "439186217",
      "impressions": 1754,
      "clicks": 0,
      "viewable": 1515,
      "eligible": 1754,
      "ctr": 0,
      "viewabilityRate": 86.3740022805017
    },
    {
      "creative": "menino02_H05_C01",
      "placement": "[P]-[468x60] - Babel- GDF - Cartao Uniforme Escolar 2026",
      "placementId": "439186217",
      "impressions": 1749,
      "clicks": 0,
      "viewable": 1504,
      "eligible": 1749,
      "ctr": 0,
      "viewabilityRate": 85.9919954259577
    },
    {
      "creative": "menina01_H04_C01",
      "placement": "[P]-[468x60] - Babel- GDF - Cartao Uniforme Escolar 2026",
      "placementId": "439186217",
      "impressions": 1505,
      "clicks": 0,
      "viewable": 1286,
      "eligible": 1505,
      "ctr": 0,
      "viewabilityRate": 85.4485049833887
    },
    {
      "creative": "menino02_H03_C01",
      "placement": "[P]-[970x250] - Babel- GDF - Cartao Uniforme Escolar 2026",
      "placementId": "439186241",
      "impressions": 1391,
      "clicks": 1,
      "viewable": 1207,
      "eligible": 1391,
      "ctr": 0.07189072609633358,
      "viewabilityRate": 86.77210639827462
    },
    {
      "creative": "(not set)",
      "placement": "[P]-[728x90] - Babel- GDF - Cartao Uniforme Escolar 2026",
      "placementId": "439186229",
      "impressions": 91,
      "clicks": 0,
      "viewable": 83,
      "eligible": 91,
      "ctr": 0,
      "viewabilityRate": 91.20879120879121
    },
    {
      "creative": "(not set)",
      "placement": "[P]-[300x250] - Babel- GDF - Cartao Uniforme Escolar 2026",
      "placementId": "439015540",
      "impressions": 77,
      "clicks": 0,
      "viewable": 59,
      "eligible": 77,
      "ctr": 0,
      "viewabilityRate": 76.62337662337663
    },
    {
      "creative": "(not set)",
      "placement": "[P]-[970x250] - Babel- GDF - Cartao Uniforme Escolar 2026",
      "placementId": "439186241",
      "impressions": 20,
      "clicks": 0,
      "viewable": 19,
      "eligible": 20,
      "ctr": 0,
      "viewabilityRate": 95
    },
    {
      "creative": "(not set)",
      "placement": "[P]-[468x60] - Babel- GDF - Cartao Uniforme Escolar 2026",
      "placementId": "439186217",
      "impressions": 3,
      "clicks": 0,
      "viewable": 2,
      "eligible": 3,
      "ctr": 0,
      "viewabilityRate": 66.66666666666666
    }
  ],
  "byDomain": []
}